my_unique_sample_package/__init__.py
my_unique_sample_package/core.py
my_unique_sample_package-0.1.0.dist-info/licenses/LICENSE
my_unique_sample_package-0.1.0.dist-info/METADATA
my_unique_sample_package-0.1.0.dist-info/WHEEL
my_unique_sample_package-0.1.0.dist-info/top_level.txt
my_unique_sample_package-0.1.0.dist-info/RECORD
